ppt_to_video-0.1.0.dist-info/licenses/LICENSE
pptx_to_video/__init__.py
pptx_to_video/__main__.py
pptx_to_video/cli.py
pptx_to_video/language_codes.py
pptx_to_video/logger.py
pptx_to_video/powerpoint.py
pptx_to_video/powerpoint_engine.py
pptx_to_video/video_constructer.py
ppt_to_video-0.1.0.dist-info/METADATA
ppt_to_video-0.1.0.dist-info/WHEEL
ppt_to_video-0.1.0.dist-info/entry_points.txt
ppt_to_video-0.1.0.dist-info/top_level.txt
ppt_to_video-0.1.0.dist-info/RECORD
