Metadata-Version: 2.4
Name: ppt-to-video
Version: 0.1.0
Summary: Add your description here
Author-email: Aaron Graham <apj_graham@yahoo.co.uk>
License: MIT License
Keywords: powerpoint,pptx,video,gtts,moviepy,automation,text-to-speech
Classifier: License :: OSI Approved :: MIT License
Classifier: Programming Language :: Python
Classifier: Programming Language :: Python :: 3
Requires-Python: >=3.10
License-File: LICENSE
Requires-Dist: deep-translator>=1.11.4
Requires-Dist: gtts>=2.5.4
Requires-Dist: moviepy>=2.2.1
Requires-Dist: python-pptx>=1.0.2
Requires-Dist: sphinx>=8.1.3
Requires-Dist: sphinx-autodoc-typehints>=3.0.1
Dynamic: license-file
